dq/__init__.py
dq/account.py
dq/client.py
dq/error.py
dq/job.py
dq/request_client.py
dq/response.py
dq_client-0.5.0.dist-info/METADATA
dq_client-0.5.0.dist-info/RECORD
dq_client-0.5.0.dist-info/WHEEL
dq_client-0.5.0.dist-info/top_level.txt
