Metadata-Version: 2.1
Name: dq-client
Version: 0.5.0
Summary: Python library which allows to use http://dataquality.pl in easy way.
Home-page: https://github.com/Algolytics/dq_client
Author: Mikołaj Olszewski
Author-email: mikolaj.olszewski@algolytics.pl
License: Apache Software License 2.0
Keywords: dataquality,dq,dq-client
Platform: UNKNOWN
Classifier: Development Status :: 2 - Pre-Alpha
Classifier: Intended Audience :: Developers
Classifier: License :: OSI Approved :: Apache Software License
Classifier: Natural Language :: English
Classifier: Programming Language :: Python :: 3
Classifier: Programming Language :: Python :: 3.3
Classifier: Programming Language :: Python :: 3.4
Classifier: Programming Language :: Python :: 3.5
Requires-Dist: requests (==2.11.1)
